kronos/__init__.py
kronos/core.py
kronos/src/.gitignore
kronos/src/__init__.py
kronos/src/command.py
kronos/src/kronos-config.yml
kronos/src/project_initializer.py
kronos/src/docker/cpu.Dockerfile
kronos/src/docker/cpu_requirements.txt
kronos/src/docker/docker-compose-cpu.yml
kronos/src/docker/docker-compose-gpu.yml
kronos/src/docker/gpu.Dockerfile
kronos/src/docker/gpu_requirements.txt
kronos/src/modules/__init__.py
kronos/src/modules/utils.py
kronos_ml-0.1.2.dist-info/LICENSE
kronos_ml-0.1.2.dist-info/METADATA
kronos_ml-0.1.2.dist-info/WHEEL
kronos_ml-0.1.2.dist-info/entry_points.txt
kronos_ml-0.1.2.dist-info/top_level.txt
kronos_ml-0.1.2.dist-info/RECORD
