Metadata-Version: 2.1
Name: kronos-ml
Version: 0.1.2
Summary: cli and toolkit for executing machine learning experiment in docker images
Home-page: UNKNOWN
Author: d-hacks
Author-email: UNKNOWN
License: UNKNOWN
Platform: UNKNOWN
Classifier: Programming Language :: Python :: 3.6
Requires-Dist: click
Requires-Dist: oyaml
